fyers_api/__init__.py
fyers_api/accessToken.py
fyers_api/config.py
fyers_api/fyersFormation.py
fyers_api/fyersLog.py
fyers_api/fyersModel.py
fyers_api/fyersService.py
fyers_api/Websocket/__init__.py
fyers_api/Websocket/constants.py
fyers_api/Websocket/ws.py
fyers_apiv2-2.0.9.dist-info/LICENSE.txt
fyers_apiv2-2.0.9.dist-info/METADATA
fyers_apiv2-2.0.9.dist-info/WHEEL
fyers_apiv2-2.0.9.dist-info/top_level.txt
fyers_apiv2-2.0.9.dist-info/RECORD
