Metadata-Version: 2.1
Name: fyers-apiv2
Version: 2.0.9
Summary: Fyers trading APIs.
Home-page: https://github.com/FyersDev/fyers-api-py
Author: Fyers-Tech
Author-email: support@fyers.in
Classifier: Programming Language :: Python :: 3
Classifier: License :: OSI Approved :: MIT License
Classifier: Operating System :: OS Independent
License-File: LICENSE.txt
